{
  "a121": "á",
  "a122": "à",
  "a123": "â",
  "a124": "ä",
  "a126": "ã",
  "a128": "ć",
  "a129": "č",
  "a12b": "é",
  "a12c": "è",
  "a12d": "ê",
  "a12e": "ë",
  "a12f": "ē",
  "a133": "î",
  "a134": "ï",
  "a135": "ī",
  "a138": "ń",
  "a139": "n",
  "a13c": "ó",
  "a13e": "ô",
  "a13f": "ö",
  "a141": "ō",
  "a149": "ú",
  "a14a": "û",
  "a14b": "ü",
  "a14c": "ū",
  "a155": "ç",
  "a15a": ".",
  "a162": "ø",
  "a173": "Ö",
  "a176": "Ü",
  "a17e": "É",
  "a221": "Ä",
  "a224": "Å",
  "a225": "[",
  "a226": "]",
  "a22b": "Ō",
  "a22f": "Č",
  "a238": "ý",
  "a23d": "å",
  "a249": "·",
  "a24e": "Ø",
  "a278": "D",
  "a279": "L",
  "a324": "ž",
  "a325": "æ",
  "a328": "b",
  "a32e": "ů",
  "b55b": "D",
  "b55c": "œ",
  "b565": "L",
  "de24": "1",
  "de25": "1",
  "de26": "1",
  "de27": "2",
  "de28": "2",
  "de29": "3",
  "de2a": "3",
  "de2b": "4",
  "de2c": "4",
  "de2d": "6",
  "de2e": "6",
  "de32": "Ċ",
  "de37": "N",
  "de44": "c",
  "de46": "d",
  "de52": "q",
  "de57": "s",
  "de58": "t",
  "de67": "α",
  "de68": "α",
  "de69": "β",
  "de6a": "β",
  "de6b": "γ",
  "de6c": "ε",
  "de6d": "ε",
  "de6f": "η",
  "de70": "θ",
  "de71": "λ",
  "de72": "μ",
  "de73": "μ",
  "de74": "μ",
  "de75": "ν",
  "de76": "ν",
  "de77": "ξ",
  "de78": "ξ",
  "de79": "ρ",
  "de7b": "σ",
  "de7c": "φ",
  "de7d": "φ",
  "de7e": "χ",
  "df21": "ψ",
  "df23": "ω",
  "df24": "N",
  "df27": "C",
  "df28": "N",
  "df29": "O",
  "df2a": "N",
  "df2b": "B",
  "df2c": "K",
  "df2d": "N",
  "df2e": "C",
  "df31": "А",
  "df32": "Б",
  "df33": "В",
  "df34": "Г",
  "df35": "Д",
  "df36": "Е",
  "df38": "Ж",
  "df39": "З",
  "df3a": "И",
  "df3b": "Й",
  "df3c": "К",
  "df3d": "Л",
  "df3e": "М",
  "df3f": "Н",
  "df40": "О",
  "df41": "П",
  "df42": "Р",
  "df43": "С",
  "df44": "Т",
  "df45": "У",
  "df46": "Ф",
  "df47": "Х",
  "df48": "Ц",
  "df4a": "Ш",
  "df4b": "Щ",
  "df4f": "Э",
  "df50": "Ю",
  "df51": "Я",
  "df52": "а",
  "df53": "б",
  "df54": "в",
  "df55": "г",
  "df56": "д",
  "df57": "е",
  "df58": "ё",
  "df59": "ж",
  "df5a": "з",
  "df5b": "и",
  "df5c": "й",
  "df5d": "к",
  "df5e": "л",
  "df5f": "м",
  "df60": "н",
  "df61": "о",
  "df62": "п",
  "df63": "р",
  "df64": "с",
  "df65": "т",
  "df66": "у",
  "df67": "ф",
  "df68": "х",
  "df69": "ц",
  "df6a": "ч",
  "df6b": "ш",
  "df6c": "щ",
  "df6d": "ъ",
  "df6e": "ы",
  "df6f": "ь",
  "df70": "э",
  "df71": "ю",
  "df72": "я",
  "e02c": "°",
  "e02f": "a",
  "e031": "p",
  "e033": "a",
  "e03a": "c",
  "e040": "e",
  "e041": "e",
  "e049": "e",
  "e050": "n",
  "e051": "o",
  "e052": "S",
  "e056": "u",
  "e057": "c",
  "e05a": "o",
  "e05b": "U",
  "e05c": "h",
  "e05d": "E",
  "e05e": "a",
  "e05f": "p",
  "e062": "Ω",
  "e069": "ss",
  "e06e": "≡",
  "e075": "↦",
  "e07e": "↑",
  "e121": "↓",
  "e12e": "Ω",
  "e12f": "⋂",
  "e130": "∆",
  "e131": "⋃",
  "e132": "ß",
  "e133": "∅",
  "e135": "∓",
  "e138": "Λ",
  "e139": "Σ",
  "e13a": "Ξ",
  "e13b": "Σ",
  "e144": "→",
  "e149": "⁰",
  "e14a": "¹",
  "e14b": "²",
  "e14c": "³",
  "e14d": "⁴",
  "e14e": "⁵",
  "e14f": "⁶",
  "e150": "⁷",
  "e151": "⁸",
  "e152": "⁹",
  "e153": "₀",
  "e154": "₁",
  "e155": "₂",
  "e156": "₃",
  "e157": "₄",
  "e158": "₅",
  "e159": "₆",
  "e15a": "₇",
  "e15b": "₈",
  "e15c": "₉",
  "e171": "A",
  "e172": "B",
  "e173": "C",
  "e174": "D",
  "e175": "E",
  "e176": "F",
  "e177": "G",
  "e178": "H",
  "e179": "I",
  "e17a": "J",
  "e17b": "K",
  "e17c": "L",
  "e17d": "M",
  "e17e": "N",
  "e221": "O",
  "e222": "P",
  "e223": "Q",
  "e224": "R",
  "e225": "S",
  "e226": "T",
  "e227": "U",
  "e228": "V",
  "e229": "W",
  "e22a": "X",
  "e22b": "Y",
  "e22c": "Z",
  "e22d": "a",
  "e22e": "b",
  "e22f": "c",
  "e230": "d",
  "e231": "e",
  "e232": "f",
  "e233": "g",
  "e234": "h",
  "e235": "i",
  "e236": "j",
  "e237": "k",
  "e238": "l",
  "e239": "m",
  "e23a": "n",
  "e23b": "o",
  "e23c": "p",
  "e23d": "q",
  "e23e": "r",
  "e23f": "s",
  "e240": "t",
  "e241": "u",
  "e242": "v",
  "e243": "w",
  "e244": "x",
  "e245": "y",
  "e246": "z",
  "e247": "A",
  "e248": "B",
  "e249": "C",
  "e24a": "D",
  "e24b": "E",
  "e24c": "F",
  "e24d": "G",
  "e24e": "H",
  "e24f": "I",
  "e250": "J",
  "e251": "K",
  "e252": "L",
  "e253": "M",
  "e254": "N",
  "e255": "O",
  "e256": "P",
  "e257": "Q",
  "e258": "R",
  "e259": "S",
  "e25a": "T",
  "e25b": "U",
  "e25c": "V",
  "e25d": "W",
  "e25e": "X",
  "e25f": "Y",
  "e260": "Z",
  "e261": "a",
  "e262": "b",
  "e263": "c",
  "e264": "d",
  "e265": "e",
  "e266": "f",
  "e267": "g",
  "e268": "h",
  "e269": "i",
  "e26a": "j",
  "e26b": "k",
  "e26c": "l",
  "e26d": "m",
  "e26e": "n",
  "e26f": "o",
  "e270": "p",
  "e271": "q",
  "e272": "r",
  "e273": "s",
  "e274": "t",
  "e275": "u",
  "e276": "v",
  "e277": "w",
  "e278": "x",
  "e279": "y",
  "e27a": "z",
  "e27b": "A",
  "e27c": "B",
  "e27d": "C",
  "e27e": "D",
  "e321": "E",
  "e322": "F",
  "e323": "G",
  "e324": "H",
  "e325": "I",
  "e326": "J",
  "e327": "K",
  "e328": "L",
  "e329": "M",
  "e32a": "N",
  "e32b": "O",
  "e32c": "P",
  "e32d": "Q",
  "e32e": "R",
  "e32f": "S",
  "e330": "T",
  "e331": "U",
  "e332": "V",
  "e333": "W",
  "e334": "X",
  "e335": "Y",
  "e336": "Z",
  "e337": "a",
  "e338": "b",
  "e339": "c",
  "e33a": "d",
  "e33b": "e",
  "e33c": "f",
  "e33d": "g",
  "e33e": "h",
  "e33f": "i",
  "e340": "j",
  "e341": "k",
  "e342": "l",
  "e343": "m",
  "e344": "n",
  "e345": "o",
  "e346": "p",
  "e347": "q",
  "e348": "r",
  "e349": "s",
  "e34a": "t",
  "e34b": "u",
  "e34c": "v",
  "e34d": "w",
  "e34e": "x",
  "e34f": "y",
  "e350": "z",
  "e351": "A",
  "e352": "B",
  "e353": "C",
  "e354": "D",
  "e355": "E",
  "e356": "F",
  "e357": "G",
  "e358": "H",
  "e359": "I",
  "e35a": "J",
  "e35b": "K",
  "e35c": "L",
  "e35d": "M",
  "e35e": "N",
  "e35f": "O",
  "e360": "P",
  "e361": "Q",
  "e362": "R",
  "e363": "S",
  "e364": "T",
  "e365": "U",
  "e366": "V",
  "e367": "W",
  "e368": "X",
  "e369": "Y",
  "e36a": "Z",
  "e36b": "a",
  "e36c": "b",
  "e36d": "c",
  "e36e": "d",
  "e36f": "e",
  "e370": "f",
  "e371": "g",
  "e372": "h",
  "e373": "i",
  "e374": "j",
  "e375": "k",
  "e376": "l",
  "e377": "m",
  "e378": "n",
  "e379": "o",
  "e37a": "p",
  "e37b": "q",
  "e37c": "r",
  "e37d": "s",
  "e37e": "t",
  "e421": "u",
  "e422": "v",
  "e423": "w",
  "e424": "x",
  "e425": "y",
  "e426": "z",
  "e427": "α",
  "e428": "β",
  "e429": "γ",
  "e42a": "δ",
  "e42b": "ε",
  "e42d": "η",
  "e42e": "θ",
  "e430": "κ",
  "e431": "λ",
  "e432": "μ",
  "e433": "ν",
  "e434": "ξ",
  "e436": "π",
  "e437": "ρ",
  "e438": "σ",
  "e439": "τ",
  "e43b": "φ",
  "e43d": "ψ",
  "e43e": "ω",
  "e447": "α",
  "e448": "β",
  "e449": "γ",
  "e44a": "δ",
  "e44b": "ε",
  "e44c": "ζ",
  "e44d": "η",
  "e44e": "θ",
  "e450": "κ",
  "e451": "λ",
  "e452": "μ",
  "e453": "ν",
  "e454": "ξ",
  "e455": "ο",
  "e456": "π",
  "e457": "ρ",
  "e458": "σ",
  "e459": "τ",
  "e45e": "ω",
  "e466": "A",
  "e467": "A",
  "e468": "B",
  "e52d": "⁽",
  "e52e": "⁾",
  "e531": "⁺",
  "e532": "⁻",
  "e540": "′",
  "e541": "″",
  "e542": "*",
  "e54a": "Ⅰ",
  "e54b": "Ⅱ",
  "e54c": "Ⅲ",
  "e54d": "Ⅳ",
  "e54f": "Ⅵ",
  "e550": "Ⅶ",
  "e551": "Ⅷ",
  "e555": "?",
  "e563": "+",
  "e564": "-",
  "e566": "0",
  "e567": "2",
  "e568": "4",
  "e569": "n",
  "e56a": "t",
  "e628": "/",
  "e62a": "~",
  "e62d": "₍",
  "e62e": "₎",
  "e62f": "[",
  "e630": "]",
  "e631": "₊",
  "e632": "₋",
  "e633": "x",
  "e635": "₌",
  "e638": "<",
  "e63a": "≦",
  "e63b": "≧",
  "e63c": "∊",
  "e63e": "∞",
  "e63f": "⊥",
  "e642": "*",
  "e643": "→",
  "e645": "↑",
  "e646": "↓",
  "e648": "⋯",
  "e64b": "Ⅱ",
  "e657": "D",
  "e663": "0",
  "e664": "1",
  "e665": "2",
  "e666": "3",
  "e667": "4",
  "e668": "5",
  "e669": "6",
  "e66a": "A",
  "e66b": "B",
  "e66c": "D",
  "e66d": "E",
  "e66e": "F",
  "e66f": "M",
  "e670": "N",
  "e671": "T",
  "e672": "c",
  "e673": "d",
  "e674": "g",
  "e675": "I",
  "e676": "k",
  "e677": "m",
  "e678": "n",
  "e679": "p",
  "e67a": "s",
  "e67b": "v",
  "e67c": "w",
  "e721": "a",
  "e722": "a",
  "e723": "e",
  "e725": "n",
  "e727": "u",
  "e728": "y",
  "e72a": "E",
  "e72b": "A",
  "e72c": "A",
  "e72d": "n",
  "e72e": "x",
  "e72f": "y",
  "e730": "k",
  "e731": "I",
  "e732": "b",
  "e733": "A",
  "e734": "B",
  "e735": "B",
  "e736": "D",
  "e737": "H",
  "e738": "M",
  "e739": "Q",
  "e73a": "Q",
  "e73b": "S",
  "e73c": "S",
  "e73d": "T",
  "e73e": "V",
  "e73f": "Y",
  "e740": "Z",
  "e741": "c",
  "e742": "f",
  "e743": "f",
  "e744": "f",
  "e745": "h",
  "e746": "h",
  "e747": "l",
  "e748": "p",
  "e749": "p",
  "e74a": "q",
  "e74b": "q",
  "e74c": "r",
  "e74d": "w",
  "e74e": "x",
  "e74f": "x",
  "e750": "x",
  "e751": "y",
  "e752": "y",
  "e753": "z",
  "e754": "z",
  "e755": "z",
  "e757": "y",
  "e758": "А",
  "e759": "И",
  "e75a": "М",
  "e75b": "П",
  "e75c": "Ф",
  "e75d": "Ч",
  "e75e": "а",
  "e75f": "в",
  "e760": "е",
  "e761": "к",
  "e762": "л",
  "e763": "н",
  "e764": "о",
  "e765": "р",
  "e766": "ъ",
  "e767": "я",
  "e768": "R",
  "e769": "m",
  "e76a": "r",
  "e76b": "r",
  "e76c": "x",
  "e76d": "y",
  "e76e": "z",
  "e76f": "B",
  "e770": "I",
  "e771": "z",
  "e772": "n",
  "e773": "a",
  "e774": "o",
  "e775": "z",
  "a421": "↔",
  "a44f": "癭",
  "a47d": "鈹",
  "a527": "炻",
  "a631": "⇀",
  "b366": "∏",
  "b37e": "∑",
  "b536": "①",
  "b537": "②",
  "b538": "③",
  "b539": "④",
  "b53a": "⑤",
  "b53b": "⑥",
  "b53c": "⑦",
  "b555": "Ⅰ",
  "b556": "Ⅱ",
  "b559": "Ⅲ",
  "b55a": "Ⅳ",
  "b55d": "Ⅵ",
  "b654": "⇒",
  "b655": "→",
  "b67a": "Ⅴ",
  "b67b": "Ⅶ",
  "b67c": "Ⅷ",
  "b67d": "Ⅸ",
  "b67e": "Ⅹ",
  "b775": "≈",
  "b776": "≃",
  "b777": "Ⓟ",
  "b77d": "⊕",
  "b822": "⇄",
  "b823": "Ⅺ",
  "b824": "Ⅻ",
  "dd23": "⇌",
  "dd25": "‹",
  "dd27": "›",
  "dd29": "↔",
  "dd2a": "S",
  "dd2b": "∖",
  "dd2d": "≥",
  "dd2e": "≤",
  "dd2f": "≌",
  "dd30": "≳",
  "dd31": "≲",
  "dd36": "∉",
  "dd37": "⊕",
  "dd38": "⇨",
  "dd3d": "Ⅰ",
  "dd3e": "Ⅱ",
  "dd3f": "Ⅲ",
  "dd40": "Ⅳ",
  "dd42": "Ⅵ",
  "dd43": "Ⅶ",
  "e060": "D",
  "e061": "L"
}